manim_presentations/Chapter.py
manim_presentations/ModularSlide.py
manim_presentations/Presentation.py
manim_presentations/__init__.py
manim_presentations-0.1.71.dist-info/METADATA
manim_presentations-0.1.71.dist-info/WHEEL
manim_presentations-0.1.71.dist-info/top_level.txt
manim_presentations-0.1.71.dist-info/RECORD
