Metadata-Version: 2.4
Name: manim-presentations
Version: 0.1.71
Summary: A Python framework for creating composable manim-slides presentations.
Author-email: S Lejoly <simon.lejoly@unamur.be>
License: MIT
Project-URL: Homepage, https://github.com/SimLej18/manim-presentations
Project-URL: Bug Reports, https://github.com/SimLej18/manim-presentations/issues
Project-URL: Source, https://github.com/SimLej18/manim-presentations
Project-URL: Documentation, https://github.com/SimLej18/manim-presentations/README.md
Keywords: manim,animations,mathematics,presentations,education,visualization
Classifier: Development Status :: 3 - Alpha
Classifier: Intended Audience :: Education
Classifier: Intended Audience :: Science/Research
Classifier: License :: OSI Approved :: MIT License
Classifier: Operating System :: OS Independent
Classifier: Programming Language :: Python :: 3
Classifier: Programming Language :: Python :: 3.8
Classifier: Programming Language :: Python :: 3.9
Classifier: Programming Language :: Python :: 3.10
Classifier: Programming Language :: Python :: 3.11
Classifier: Topic :: Scientific/Engineering :: Mathematics
Classifier: Topic :: Scientific/Engineering :: Visualization
Classifier: Topic :: Multimedia :: Graphics
Requires-Python: >=3.8
Requires-Dist: manim
Requires-Dist: manim-slides
Provides-Extra: dev
Requires-Dist: pytest; extra == "dev"
Requires-Dist: black; extra == "dev"
Requires-Dist: flake8; extra == "dev"
